ckanext_json_viewer-1.0.4-py3.12-nspkg.pth
ckanext/json_viewer/__init__.py
ckanext/json_viewer/config.py
ckanext/json_viewer/config_declaration.yml
ckanext/json_viewer/helpers.py
ckanext/json_viewer/plugin.py
ckanext/json_viewer/assets/webassets.yml
ckanext/json_viewer/assets/css/json_viewer.css
ckanext/json_viewer/assets/js/vendor/json-viewer.min.js
ckanext/json_viewer/templates/json_form.html
ckanext/json_viewer/templates/json_view.html
ckanext/json_viewer/templates/package/snippets/view_form.html
ckanext/json_viewer/tests/__init__.py
ckanext/json_viewer/tests/test_plugin.py
ckanext_json_viewer-1.0.4.dist-info/licenses/LICENSE
ckanext_json_viewer-1.0.4.dist-info/METADATA
ckanext_json_viewer-1.0.4.dist-info/WHEEL
ckanext_json_viewer-1.0.4.dist-info/entry_points.txt
ckanext_json_viewer-1.0.4.dist-info/namespace_packages.txt
ckanext_json_viewer-1.0.4.dist-info/top_level.txt
ckanext_json_viewer-1.0.4.dist-info/RECORD
