Metadata-Version: 2.4
Name: ckanext-json-viewer
Version: 1.0.4
Summary: JSON tree preview
Author-email: Oleksandr Cherniavskyi <mutantsan@gmail.com>
License: AGPL
Project-URL: Homepage, https://github.com/DataShades/ckanext-json-viewer
Keywords: CKAN
Classifier: Development Status :: 4 - Beta
Classifier: License :: OSI Approved :: GNU Affero General Public License v3 or later (AGPLv3+)
Classifier: Programming Language :: Python :: 3.8
Classifier: Programming Language :: Python :: 3.9
Classifier: Programming Language :: Python :: 3.10
License-File: LICENSE
Dynamic: license-file
